[{"StartedAt":"2022-12-20T16:58:18.958129401Z","EndedAt":"2022-12-20T17:01:48.968510726Z","FailedTxs":0,"EvictedTxs":0,"SuccessfulTxs":300,"AlreadySeenTxs":170,"AlreadyRejectedTxs":19,"RequestedTxs":422,"RerequestedTxs":107,"LostTxs":0,"FailedResponses":0,"SentTransactionBytes":1897194,"SentStateBytes":260312,"ReceivedTxBytes":2189070,"ReceivedStateBytes":275338},{"StartedAt":"2022-12-20T16:58:18.958129401Z","EndedAt":"2022-12-20T17:02:28.967830798Z","FailedTxs":0,"EvictedTxs":0,"SuccessfulTxs":500,"AlreadySeenTxs":221,"AlreadyRejectedTxs":25,"RequestedTxs":599,"RerequestedTxs":129,"LostTxs":0,"FailedResponses":0,"SentTransactionBytes":3068440,"SentStateBytes":393778,"ReceivedTxBytes":3143280,"ReceivedStateBytes":415318},{"StartedAt":"2022-12-20T16:58:18.958129401Z","EndedAt":"2022-12-20T17:02:58.968425263Z","FailedTxs":0,"EvictedTxs":0,"SuccessfulTxs":700,"AlreadySeenTxs":273,"AlreadyRejectedTxs":27,"RequestedTxs":777,"RerequestedTxs":146,"LostTxs":0,"FailedResponses":0,"SentTransactionBytes":3884196,"SentStateBytes":530446,"ReceivedTxBytes":4086264,"ReceivedStateBytes":551258},{"StartedAt":"2022-12-20T16:58:18.958129401Z","EndedAt":"2022-12-20T17:03:38.968129336Z","FailedTxs":0,"EvictedTxs":0,"SuccessfulTxs":1000,"AlreadySeenTxs":344,"AlreadyRejectedTxs":27,"RequestedTxs":1037,"RerequestedTxs":172,"LostTxs":2,"FailedResponses":0,"SentTransactionBytes":5122798,"SentStateBytes":731224,"ReceivedTxBytes":5463320,"ReceivedStateBytes":757318},{"StartedAt":"2022-12-20T16:58:18.958129401Z","EndedAt":"2022-12-20T17:04:08.968342102Z","FailedTxs":0,"EvictedTxs":0,"SuccessfulTxs":1200,"AlreadySeenTxs":396,"AlreadyRejectedTxs":27,"RequestedTxs":1215,"RerequestedTxs":190,"LostTxs":2,"FailedResponses":0,"SentTransactionBytes":6267850,"SentStateBytes":867756,"ReceivedTxBytes":6398820,"ReceivedStateBytes":886432},{"StartedAt":"2022-12-20T16:58:18.958129401Z","EndedAt":"2022-12-20T17:04:48.96854971Z","FailedTxs":0,"EvictedTxs":0,"SuccessfulTxs":1400,"AlreadySeenTxs":522,"AlreadyRejectedTxs":27,"RequestedTxs":1467,"RerequestedTxs":284,"LostTxs":2,"FailedResponses":0,"SentTransactionBytes":7304384,"SentStateBytes":999768,"ReceivedTxBytes":7611228,"ReceivedStateBytes":1017746},{"StartedAt":"2022-12-20T16:58:18.958129401Z","EndedAt":"2022-12-20T17:05:28.968750243Z","FailedTxs":0,"EvictedTxs":0,"SuccessfulTxs":1700,"AlreadySeenTxs":808,"AlreadyRejectedTxs":53,"RequestedTxs":1942,"RerequestedTxs":517,"LostTxs":2,"FailedResponses":0,"SentTransactionBytes":8905960,"SentStateBytes":1203126,"ReceivedTxBytes":9890106,"ReceivedStateBytes":1224094},{"StartedAt":"2022-12-20T16:58:18.958129401Z","EndedAt":"2022-12-20T17:05:58.968012532Z","FailedTxs":0,"EvictedTxs":0,"SuccessfulTxs":1900,"AlreadySeenTxs":928,"AlreadyRejectedTxs":53,"RequestedTxs":2189,"RerequestedTxs":604,"LostTxs":2,"FailedResponses":0,"SentTransactionBytes":9800298,"SentStateBytes":1337434,"ReceivedTxBytes":11080062,"ReceivedStateBytes":1361952},{"StartedAt":"2022-12-20T16:58:18.958129401Z","EndedAt":"2022-12-20T17:06:38.968372795Z","FailedTxs":0,"EvictedTxs":0,"SuccessfulTxs":2100,"AlreadySeenTxs":972,"AlreadyRejectedTxs":69,"RequestedTxs":2358,"RerequestedTxs":610,"LostTxs":2,"FailedResponses":0,"SentTransactionBytes":10533730,"SentStateBytes":1468680,"ReceivedTxBytes":12045498,"ReceivedStateBytes":1497668},{"StartedAt":"2022-12-20T16:58:18.958129401Z","EndedAt":"2022-12-20T17:07:08.968541217Z","FailedTxs":0,"EvictedTxs":0,"SuccessfulTxs":2200,"AlreadySeenTxs":972,"AlreadyRejectedTxs":69,"RequestedTxs":2358,"RerequestedTxs":610,"LostTxs":2,"FailedResponses":0,"SentTransactionBytes":10533730,"SentStateBytes":1468680,"ReceivedTxBytes":12045498,"ReceivedStateBytes":1497668},{"StartedAt":"2022-12-20T16:58:18.958129401Z","EndedAt":"2022-12-20T17:07:48.968376759Z","FailedTxs":0,"EvictedTxs":0,"SuccessfulTxs":3084,"AlreadySeenTxs":2037,"AlreadyRejectedTxs":69,"RequestedTxs":4658,"RerequestedTxs":1311,"LostTxs":10,"FailedResponses":0,"SentTransactionBytes":27042636,"SentStateBytes":2671944,"ReceivedTxBytes":29308476,"ReceivedStateBytes":2823238},{"StartedAt":"2022-12-20T16:58:18.958129401Z","EndedAt":"2022-12-20T17:08:18.96849948Z","FailedTxs":0,"EvictedTxs":0,"SuccessfulTxs":3968,"AlreadySeenTxs":2413,"AlreadyRejectedTxs":69,"RequestedTxs":5588,"RerequestedTxs":1533,"LostTxs":10,"FailedResponses":0,"SentTransactionBytes":34703108,"SentStateBytes":3255460,"ReceivedTxBytes":36461292,"ReceivedStateBytes":3382538},{"StartedAt":"2022-12-20T16:58:18.958129401Z","EndedAt":"2022-12-20T17:08:58.968334769Z","FailedTxs":0,"EvictedTxs":0,"SuccessfulTxs":6620,"AlreadySeenTxs":3752,"AlreadyRejectedTxs":69,"RequestedTxs":8554,"RerequestedTxs":2323,"LostTxs":19,"FailedResponses":0,"SentTransactionBytes":56418236,"SentStateBytes":4825874,"ReceivedTxBytes":59060540,"ReceivedStateBytes":5127678},{"StartedAt":"2022-12-20T16:58:18.958129401Z","EndedAt":"2022-12-20T17:09:38.968326956Z","FailedTxs":0,"EvictedTxs":0,"SuccessfulTxs":8388,"AlreadySeenTxs":4504,"AlreadyRejectedTxs":69,"RequestedTxs":10433,"RerequestedTxs":2764,"LostTxs":23,"FailedResponses":0,"SentTransactionBytes":73028284,"SentStateBytes":5923456,"ReceivedTxBytes":73331948,"ReceivedStateBytes":6250116},{"StartedAt":"2022-12-20T16:58:18.958129401Z","EndedAt":"2022-12-20T17:10:08.968114063Z","FailedTxs":0,"EvictedTxs":0,"SuccessfulTxs":10156,"AlreadySeenTxs":5175,"AlreadyRejectedTxs":69,"RequestedTxs":12230,"RerequestedTxs":3122,"LostTxs":30,"FailedResponses":0,"SentTransactionBytes":84088340,"SentStateBytes":6932348,"ReceivedTxBytes":87055772,"ReceivedStateBytes":7381298},{"StartedAt":"2022-12-20T16:58:18.958129401Z","EndedAt":"2022-12-20T17:10:48.968452435Z","FailedTxs":0,"EvictedTxs":0,"SuccessfulTxs":11936,"AlreadySeenTxs":6145,"AlreadyRejectedTxs":69,"RequestedTxs":14305,"RerequestedTxs":3765,"LostTxs":38,"FailedResponses":0,"SentTransactionBytes":97738012,"SentStateBytes":8028786,"ReceivedTxBytes":102656212,"ReceivedStateBytes":8550468}]