{"StartedAt":"2022-12-22T14:53:28.276512155Z","EndedAt":"2022-12-22T14:55:28.28609989Z","FailedTxs":0,"EvictedTxs":0,"SuccessfulTxs":300,"AlreadySeenTxs":810,"AlreadyRejectedTxs":8,"RequestedTxs":1061,"RerequestedTxs":703,"LostTxs":44,"FailedResponses":1,"SentTransactionBytes":68012312,"SentStateBytes":929944,"ReceivedTxBytes":78560368,"ReceivedStateBytes":920016},{"StartedAt":"2022-12-22T14:53:28.276512155Z","EndedAt":"2022-12-22T14:56:08.285682251Z","FailedTxs":0,"EvictedTxs":0,"SuccessfulTxs":500,"AlreadySeenTxs":919,"AlreadyRejectedTxs":8,"RequestedTxs":1286,"RerequestedTxs":775,"LostTxs":49,"FailedResponses":1,"SentTransactionBytes":88914288,"SentStateBytes":1304336,"ReceivedTxBytes":97132712,"ReceivedStateBytes":1236426},{"StartedAt":"2022-12-22T14:53:28.276512155Z","EndedAt":"2022-12-22T14:56:48.285929563Z","FailedTxs":0,"EvictedTxs":0,"SuccessfulTxs":600,"AlreadySeenTxs":1005,"AlreadyRejectedTxs":8,"RequestedTxs":1436,"RerequestedTxs":836,"LostTxs":55,"FailedResponses":2,"SentTransactionBytes":112663592,"SentStateBytes":1552854,"ReceivedTxBytes":110398672,"ReceivedStateBytes":1555014},{"StartedAt":"2022-12-22T14:53:28.276512155Z","EndedAt":"2022-12-22T14:57:28.286116774Z","FailedTxs":0,"EvictedTxs":0,"SuccessfulTxs":800,"AlreadySeenTxs":1084,"AlreadyRejectedTxs":8,"RequestedTxs":1635,"RerequestedTxs":866,"LostTxs":75,"FailedResponses":2,"SentTransactionBytes":130135832,"SentStateBytes":1919358,"ReceivedTxBytes":128323896,"ReceivedStateBytes":1977270},{"StartedAt":"2022-12-22T14:53:28.276512155Z","EndedAt":"2022-12-22T14:58:08.28636613Z","FailedTxs":0,"EvictedTxs":0,"SuccessfulTxs":1000,"AlreadySeenTxs":1180,"AlreadyRejectedTxs":8,"RequestedTxs":1791,"RerequestedTxs":910,"LostTxs":111,"FailedResponses":2,"SentTransactionBytes":140036768,"SentStateBytes":2110962,"ReceivedTxBytes":140942736,"ReceivedStateBytes":2241178}