{"StartedAt":"2022-12-22T14:53:28.304638049Z","EndedAt":"2022-12-22T14:55:28.316307212Z","FailedTxs":0,"EvictedTxs":0,"SuccessfulTxs":300,"AlreadySeenTxs":731,"AlreadyRejectedTxs":0,"RequestedTxs":976,"RerequestedTxs":649,"LostTxs":31,"FailedResponses":14,"SentTransactionBytes":75324768,"SentStateBytes":973506,"ReceivedTxBytes":72930424,"ReceivedStateBytes":820080},{"StartedAt":"2022-12-22T14:53:28.304638049Z","EndedAt":"2022-12-22T14:56:08.315766437Z","FailedTxs":0,"EvictedTxs":0,"SuccessfulTxs":500,"AlreadySeenTxs":832,"AlreadyRejectedTxs":0,"RequestedTxs":1194,"RerequestedTxs":706,"LostTxs":47,"FailedResponses":14,"SentTransactionBytes":95450200,"SentStateBytes":1296522,"ReceivedTxBytes":90920360,"ReceivedStateBytes":1127554},{"StartedAt":"2022-12-22T14:53:28.304638049Z","EndedAt":"2022-12-22T14:56:48.315784288Z","FailedTxs":0,"EvictedTxs":0,"SuccessfulTxs":600,"AlreadySeenTxs":980,"AlreadyRejectedTxs":0,"RequestedTxs":1408,"RerequestedTxs":791,"LostTxs":89,"FailedResponses":15,"SentTransactionBytes":115899192,"SentStateBytes":1551490,"ReceivedTxBytes":108263176,"ReceivedStateBytes":1434624},{"StartedAt":"2022-12-22T14:53:28.304638049Z","EndedAt":"2022-12-22T14:57:18.315421546Z","FailedTxs":0,"EvictedTxs":0,"SuccessfulTxs":800,"AlreadySeenTxs":1002,"AlreadyRejectedTxs":0,"RequestedTxs":1547,"RerequestedTxs":800,"LostTxs":89,"FailedResponses":15,"SentTransactionBytes":138224832,"SentStateBytes":1872320,"ReceivedTxBytes":121529136,"ReceivedStateBytes":1706288},{"StartedAt":"2022-12-22T14:53:28.304638049Z","EndedAt":"2022-12-22T14:58:08.315607823Z","FailedTxs":0,"EvictedTxs":0,"SuccessfulTxs":1000,"AlreadySeenTxs":1019,"AlreadyRejectedTxs":0,"RequestedTxs":1630,"RerequestedTxs":807,"LostTxs":92,"FailedResponses":15,"SentTransactionBytes":162232984,"SentStateBytes":2079312,"ReceivedTxBytes":130006408,"ReceivedStateBytes":1953854}