{"StartedAt":"2022-12-22T14:53:28.29558513Z","EndedAt":"2022-12-22T14:55:18.305673397Z","FailedTxs":0,"EvictedTxs":0,"SuccessfulTxs":200,"AlreadySeenTxs":685,"AlreadyRejectedTxs":0,"RequestedTxs":870,"RerequestedTxs":590,"LostTxs":32,"FailedResponses":0,"SentTransactionBytes":48598712,"SentStateBytes":718904,"ReceivedTxBytes":63547184,"ReceivedStateBytes":668732},{"StartedAt":"2022-12-22T14:53:28.29558513Z","EndedAt":"2022-12-22T14:55:58.30638756Z","FailedTxs":0,"EvictedTxs":0,"SuccessfulTxs":400,"AlreadySeenTxs":788,"AlreadyRejectedTxs":0,"RequestedTxs":1095,"RerequestedTxs":670,"LostTxs":35,"FailedResponses":0,"SentTransactionBytes":78819216,"SentStateBytes":1100840,"ReceivedTxBytes":83025496,"ReceivedStateBytes":1062212},{"StartedAt":"2022-12-22T14:53:28.29558513Z","EndedAt":"2022-12-22T14:56:38.306182452Z","FailedTxs":0,"EvictedTxs":0,"SuccessfulTxs":600,"AlreadySeenTxs":902,"AlreadyRejectedTxs":0,"RequestedTxs":1331,"RerequestedTxs":757,"LostTxs":35,"FailedResponses":1,"SentTransactionBytes":100238888,"SentStateBytes":1431034,"ReceivedTxBytes":103215640,"ReceivedStateBytes":1489754},{"StartedAt":"2022-12-22T14:53:28.29558513Z","EndedAt":"2022-12-22T14:57:18.305920707Z","FailedTxs":0,"EvictedTxs":0,"SuccessfulTxs":800,"AlreadySeenTxs":1086,"AlreadyRejectedTxs":0,"RequestedTxs":1630,"RerequestedTxs":885,"LostTxs":53,"FailedResponses":1,"SentTransactionBytes":124700024,"SentStateBytes":1820564,"ReceivedTxBytes":126900232,"ReceivedStateBytes":1835686},{"StartedAt":"2022-12-22T14:53:28.29558513Z","EndedAt":"2022-12-22T14:57:58.305859941Z","FailedTxs":0,"EvictedTxs":0,"SuccessfulTxs":900,"AlreadySeenTxs":1131,"AlreadyRejectedTxs":0,"RequestedTxs":1743,"RerequestedTxs":921,"LostTxs":53,"FailedResponses":1,"SentTransactionBytes":140230904,"SentStateBytes":2018642,"ReceivedTxBytes":137254152,"ReceivedStateBytes":2076232}