{"StartedAt":"2022-12-22T15:26:28.39354608Z","EndedAt":"2022-12-22T15:27:28.403303485Z","FailedTxs":0,"EvictedTxs":0,"SuccessfulTxs":0,"AlreadySeenTxs":3,"AlreadyRejectedTxs":0,"RequestedTxs":48,"RerequestedTxs":0,"LostTxs":0,"FailedResponses":0,"SentTransactionBytes":2912040,"SentStateBytes":27674,"ReceivedTxBytes":1617800,"ReceivedStateBytes":16786},{"StartedAt":"2022-12-22T15:26:28.39354608Z","EndedAt":"2022-12-22T15:28:08.404188309Z","FailedTxs":0,"EvictedTxs":0,"SuccessfulTxs":0,"AlreadySeenTxs":268,"AlreadyRejectedTxs":0,"RequestedTxs":151,"RerequestedTxs":67,"LostTxs":10,"FailedResponses":0,"SentTransactionBytes":25302392,"SentStateBytes":160318,"ReceivedTxBytes":23684592,"ReceivedStateBytes":87188}