[{"StartedAt":"2022-12-20T17:23:11.476404602Z","EndedAt":"2022-12-20T17:26:41.488811935Z","FailedTxs":0,"EvictedTxs":0,"SuccessfulTxs":300,"AlreadySeenTxs":5571,"AlreadyRejectedTxs":0,"RequestedTxs":0,"RerequestedTxs":0,"LostTxs":0,"FailedResponses":0,"SentTransactionBytes":22440774,"SentStateBytes":0,"ReceivedTxBytes":22545550,"ReceivedStateBytes":0},{"StartedAt":"2022-12-20T17:23:11.476404602Z","EndedAt":"2022-12-20T17:27:11.48936704Z","FailedTxs":0,"EvictedTxs":0,"SuccessfulTxs":500,"AlreadySeenTxs":8326,"AlreadyRejectedTxs":0,"RequestedTxs":0,"RerequestedTxs":0,"LostTxs":0,"FailedResponses":0,"SentTransactionBytes":33674258,"SentStateBytes":0,"ReceivedTxBytes":33648064,"ReceivedStateBytes":0},{"StartedAt":"2022-12-20T17:23:11.476404602Z","EndedAt":"2022-12-20T17:27:51.48852374Z","FailedTxs":0,"EvictedTxs":0,"SuccessfulTxs":700,"AlreadySeenTxs":10927,"AlreadyRejectedTxs":0,"RequestedTxs":0,"RerequestedTxs":0,"LostTxs":0,"FailedResponses":0,"SentTransactionBytes":44889032,"SentStateBytes":0,"ReceivedTxBytes":44922710,"ReceivedStateBytes":0},{"StartedAt":"2022-12-20T17:23:11.476404602Z","EndedAt":"2022-12-20T17:28:31.4891556Z","FailedTxs":0,"EvictedTxs":0,"SuccessfulTxs":1000,"AlreadySeenTxs":15083,"AlreadyRejectedTxs":0,"RequestedTxs":0,"RerequestedTxs":0,"LostTxs":0,"FailedResponses":0,"SentTransactionBytes":61735516,"SentStateBytes":0,"ReceivedTxBytes":61761710,"ReceivedStateBytes":0},{"StartedAt":"2022-12-20T17:23:11.476404602Z","EndedAt":"2022-12-20T17:29:01.48872413Z","FailedTxs":0,"EvictedTxs":0,"SuccessfulTxs":1200,"AlreadySeenTxs":17898,"AlreadyRejectedTxs":0,"RequestedTxs":0,"RerequestedTxs":0,"LostTxs":0,"FailedResponses":0,"SentTransactionBytes":72965258,"SentStateBytes":0,"ReceivedTxBytes":73114938,"ReceivedStateBytes":0},{"StartedAt":"2022-12-20T17:23:11.476404602Z","EndedAt":"2022-12-20T17:29:41.489167916Z","FailedTxs":0,"EvictedTxs":0,"SuccessfulTxs":1400,"AlreadySeenTxs":20645,"AlreadyRejectedTxs":0,"RequestedTxs":0,"RerequestedTxs":0,"LostTxs":0,"FailedResponses":0,"SentTransactionBytes":84195000,"SentStateBytes":0,"ReceivedTxBytes":84180032,"ReceivedStateBytes":0},{"StartedAt":"2022-12-20T17:23:11.476404602Z","EndedAt":"2022-12-20T17:30:11.488710967Z","FailedTxs":0,"EvictedTxs":0,"SuccessfulTxs":1600,"AlreadySeenTxs":23386,"AlreadyRejectedTxs":0,"RequestedTxs":0,"RerequestedTxs":0,"LostTxs":0,"FailedResponses":0,"SentTransactionBytes":95421000,"SentStateBytes":0,"ReceivedTxBytes":95256352,"ReceivedStateBytes":0},{"StartedAt":"2022-12-20T17:23:11.476404602Z","EndedAt":"2022-12-20T17:30:51.488528346Z","FailedTxs":0,"EvictedTxs":0,"SuccessfulTxs":1900,"AlreadySeenTxs":27569,"AlreadyRejectedTxs":0,"RequestedTxs":0,"RerequestedTxs":0,"LostTxs":0,"FailedResponses":0,"SentTransactionBytes":112245032,"SentStateBytes":0,"ReceivedTxBytes":112166450,"ReceivedStateBytes":0},{"StartedAt":"2022-12-20T17:23:11.476404602Z","EndedAt":"2022-12-20T17:31:31.48925142Z","FailedTxs":0,"EvictedTxs":0,"SuccessfulTxs":2100,"AlreadySeenTxs":30402,"AlreadyRejectedTxs":0,"RequestedTxs":0,"RerequestedTxs":0,"LostTxs":0,"FailedResponses":0,"SentTransactionBytes":123471032,"SentStateBytes":0,"ReceivedTxBytes":123613228,"ReceivedStateBytes":0},{"StartedAt":"2022-12-20T17:23:11.476404602Z","EndedAt":"2022-12-20T17:32:01.489253711Z","FailedTxs":0,"EvictedTxs":0,"SuccessfulTxs":2200,"AlreadySeenTxs":30402,"AlreadyRejectedTxs":0,"RequestedTxs":0,"RerequestedTxs":0,"LostTxs":0,"FailedResponses":0,"SentTransactionBytes":123471032,"SentStateBytes":0,"ReceivedTxBytes":123616970,"ReceivedStateBytes":0},{"StartedAt":"2022-12-20T17:23:11.476404602Z","EndedAt":"2022-12-20T17:32:41.489453093Z","FailedTxs":0,"EvictedTxs":0,"SuccessfulTxs":3084,"AlreadySeenTxs":53092,"AlreadyRejectedTxs":0,"RequestedTxs":0,"RerequestedTxs":0,"LostTxs":0,"FailedResponses":0,"SentTransactionBytes":285364194,"SentStateBytes":0,"ReceivedTxBytes":265379220,"ReceivedStateBytes":0},{"StartedAt":"2022-12-20T17:23:11.476404602Z","EndedAt":"2022-12-20T17:33:11.488589739Z","FailedTxs":0,"EvictedTxs":0,"SuccessfulTxs":3968,"AlreadySeenTxs":63092,"AlreadyRejectedTxs":0,"RequestedTxs":0,"RerequestedTxs":0,"LostTxs":0,"FailedResponses":0,"SentTransactionBytes":362425234,"SentStateBytes":0,"ReceivedTxBytes":327547116,"ReceivedStateBytes":0},{"StartedAt":"2022-12-20T17:23:11.476404602Z","EndedAt":"2022-12-20T17:33:51.489053351Z","FailedTxs":0,"EvictedTxs":0,"SuccessfulTxs":6620,"AlreadySeenTxs":94514,"AlreadyRejectedTxs":0,"RequestedTxs":0,"RerequestedTxs":0,"LostTxs":0,"FailedResponses":0,"SentTransactionBytes":591549210,"SentStateBytes":0,"ReceivedTxBytes":523154388,"ReceivedStateBytes":0},{"StartedAt":"2022-12-20T17:23:11.476404602Z","EndedAt":"2022-12-20T17:34:21.488950006Z","FailedTxs":0,"EvictedTxs":0,"SuccessfulTxs":7504,"AlreadySeenTxs":104776,"AlreadyRejectedTxs":0,"RequestedTxs":0,"RerequestedTxs":0,"LostTxs":0,"FailedResponses":0,"SentTransactionBytes":671473658,"SentStateBytes":0,"ReceivedTxBytes":586902292,"ReceivedStateBytes":0},{"StartedAt":"2022-12-20T17:23:11.476404602Z","EndedAt":"2022-12-20T17:35:01.488757937Z","FailedTxs":0,"EvictedTxs":0,"SuccessfulTxs":10156,"AlreadySeenTxs":131824,"AlreadyRejectedTxs":0,"RequestedTxs":0,"RerequestedTxs":0,"LostTxs":0,"FailedResponses":0,"SentTransactionBytes":876389858,"SentStateBytes":0,"ReceivedTxBytes":757811244,"ReceivedStateBytes":0},{"StartedAt":"2022-12-20T17:23:11.476404602Z","EndedAt":"2022-12-20T17:35:31.489201001Z","FailedTxs":0,"EvictedTxs":0,"SuccessfulTxs":11040,"AlreadySeenTxs":152889,"AlreadyRejectedTxs":0,"RequestedTxs":0,"RerequestedTxs":0,"LostTxs":0,"FailedResponses":0,"SentTransactionBytes":997149242,"SentStateBytes":0,"ReceivedTxBytes":885666404,"ReceivedStateBytes":0},{"StartedAt":"2022-12-20T17:23:11.476404602Z","EndedAt":"2022-12-20T17:36:01.488637438Z","FailedTxs":0,"EvictedTxs":0,"SuccessfulTxs":12808,"AlreadySeenTxs":174786,"AlreadyRejectedTxs":0,"RequestedTxs":0,"RerequestedTxs":0,"LostTxs":0,"FailedResponses":0,"SentTransactionBytes":1143029042,"SentStateBytes":0,"ReceivedTxBytes":1019853004,"ReceivedStateBytes":0}]