[{"StartedAt":"2022-12-20T17:23:11.404644174Z","EndedAt":"2022-12-20T17:26:21.412040555Z","FailedTxs":0,"EvictedTxs":0,"SuccessfulTxs":200,"AlreadySeenTxs":5533,"AlreadyRejectedTxs":0,"RequestedTxs":0,"RerequestedTxs":0,"LostTxs":0,"FailedResponses":0,"SentTransactionBytes":22059090,"SentStateBytes":0,"ReceivedTxBytes":22328514,"ReceivedStateBytes":0},{"StartedAt":"2022-12-20T17:23:11.404644174Z","EndedAt":"2022-12-20T17:27:01.41225336Z","FailedTxs":0,"EvictedTxs":0,"SuccessfulTxs":400,"AlreadySeenTxs":9134,"AlreadyRejectedTxs":0,"RequestedTxs":0,"RerequestedTxs":0,"LostTxs":0,"FailedResponses":0,"SentTransactionBytes":37292772,"SentStateBytes":0,"ReceivedTxBytes":37943880,"ReceivedStateBytes":0},{"StartedAt":"2022-12-20T17:23:11.404644174Z","EndedAt":"2022-12-20T17:27:31.412840917Z","FailedTxs":0,"EvictedTxs":0,"SuccessfulTxs":600,"AlreadySeenTxs":12922,"AlreadyRejectedTxs":0,"RequestedTxs":0,"RerequestedTxs":0,"LostTxs":0,"FailedResponses":0,"SentTransactionBytes":52268256,"SentStateBytes":0,"ReceivedTxBytes":52896912,"ReceivedStateBytes":0},{"StartedAt":"2022-12-20T17:23:11.404644174Z","EndedAt":"2022-12-20T17:28:11.412127977Z","FailedTxs":0,"EvictedTxs":0,"SuccessfulTxs":900,"AlreadySeenTxs":18560,"AlreadyRejectedTxs":0,"RequestedTxs":0,"RerequestedTxs":0,"LostTxs":0,"FailedResponses":0,"SentTransactionBytes":74727740,"SentStateBytes":0,"ReceivedTxBytes":75337686,"ReceivedStateBytes":0},{"StartedAt":"2022-12-20T17:23:11.404644174Z","EndedAt":"2022-12-20T17:28:41.412130263Z","FailedTxs":0,"EvictedTxs":0,"SuccessfulTxs":1000,"AlreadySeenTxs":20408,"AlreadyRejectedTxs":0,"RequestedTxs":0,"RerequestedTxs":0,"LostTxs":0,"FailedResponses":0,"SentTransactionBytes":82200514,"SentStateBytes":0,"ReceivedTxBytes":82638328,"ReceivedStateBytes":0},{"StartedAt":"2022-12-20T17:23:11.404644174Z","EndedAt":"2022-12-20T17:29:21.412333236Z","FailedTxs":0,"EvictedTxs":0,"SuccessfulTxs":1300,"AlreadySeenTxs":25831,"AlreadyRejectedTxs":0,"RequestedTxs":0,"RerequestedTxs":0,"LostTxs":0,"FailedResponses":0,"SentTransactionBytes":104663740,"SentStateBytes":0,"ReceivedTxBytes":105225040,"ReceivedStateBytes":0},{"StartedAt":"2022-12-20T17:23:11.404644174Z","EndedAt":"2022-12-20T17:30:01.41221533Z","FailedTxs":0,"EvictedTxs":0,"SuccessfulTxs":1600,"AlreadySeenTxs":31497,"AlreadyRejectedTxs":0,"RequestedTxs":0,"RerequestedTxs":0,"LostTxs":0,"FailedResponses":0,"SentTransactionBytes":127119482,"SentStateBytes":0,"ReceivedTxBytes":127677040,"ReceivedStateBytes":0},{"StartedAt":"2022-12-20T17:23:11.404644174Z","EndedAt":"2022-12-20T17:30:41.412210554Z","FailedTxs":0,"EvictedTxs":0,"SuccessfulTxs":1800,"AlreadySeenTxs":35118,"AlreadyRejectedTxs":0,"RequestedTxs":0,"RerequestedTxs":0,"LostTxs":0,"FailedResponses":0,"SentTransactionBytes":142083740,"SentStateBytes":0,"ReceivedTxBytes":142959368,"ReceivedStateBytes":0},{"StartedAt":"2022-12-20T17:23:11.404644174Z","EndedAt":"2022-12-20T17:31:11.412255339Z","FailedTxs":0,"EvictedTxs":0,"SuccessfulTxs":2000,"AlreadySeenTxs":38958,"AlreadyRejectedTxs":0,"RequestedTxs":0,"RerequestedTxs":0,"LostTxs":0,"FailedResponses":0,"SentTransactionBytes":157047998,"SentStateBytes":0,"ReceivedTxBytes":158114468,"ReceivedStateBytes":0},{"StartedAt":"2022-12-20T17:23:11.404644174Z","EndedAt":"2022-12-20T17:31:41.41233536Z","FailedTxs":0,"EvictedTxs":0,"SuccessfulTxs":2200,"AlreadySeenTxs":40860,"AlreadyRejectedTxs":0,"RequestedTxs":0,"RerequestedTxs":0,"LostTxs":0,"FailedResponses":0,"SentTransactionBytes":164535740,"SentStateBytes":0,"ReceivedTxBytes":165628404,"ReceivedStateBytes":0},{"StartedAt":"2022-12-20T17:23:11.404644174Z","EndedAt":"2022-12-20T17:32:21.411904311Z","FailedTxs":0,"EvictedTxs":0,"SuccessfulTxs":2200,"AlreadySeenTxs":52522,"AlreadyRejectedTxs":0,"RequestedTxs":0,"RerequestedTxs":0,"LostTxs":0,"FailedResponses":0,"SentTransactionBytes":242248298,"SentStateBytes":0,"ReceivedTxBytes":239668874,"ReceivedStateBytes":0},{"StartedAt":"2022-12-20T17:23:11.404644174Z","EndedAt":"2022-12-20T17:33:01.412315858Z","FailedTxs":0,"EvictedTxs":0,"SuccessfulTxs":3968,"AlreadySeenTxs":88027,"AlreadyRejectedTxs":0,"RequestedTxs":0,"RerequestedTxs":0,"LostTxs":0,"FailedResponses":0,"SentTransactionBytes":450726218,"SentStateBytes":0,"ReceivedTxBytes":455371816,"ReceivedStateBytes":0},{"StartedAt":"2022-12-20T17:23:11.404644174Z","EndedAt":"2022-12-20T17:33:31.412185216Z","FailedTxs":0,"EvictedTxs":0,"SuccessfulTxs":5736,"AlreadySeenTxs":102040,"AlreadyRejectedTxs":0,"RequestedTxs":0,"RerequestedTxs":0,"LostTxs":0,"FailedResponses":0,"SentTransactionBytes":542503578,"SentStateBytes":0,"ReceivedTxBytes":540315784,"ReceivedStateBytes":0},{"StartedAt":"2022-12-20T17:23:11.404644174Z","EndedAt":"2022-12-20T17:34:11.412281515Z","FailedTxs":0,"EvictedTxs":0,"SuccessfulTxs":7504,"AlreadySeenTxs":147565,"AlreadyRejectedTxs":0,"RequestedTxs":0,"RerequestedTxs":0,"LostTxs":0,"FailedResponses":0,"SentTransactionBytes":805720362,"SentStateBytes":0,"ReceivedTxBytes":817615744,"ReceivedStateBytes":0},{"StartedAt":"2022-12-20T17:23:11.404644174Z","EndedAt":"2022-12-20T17:34:41.412206629Z","FailedTxs":0,"EvictedTxs":0,"SuccessfulTxs":8388,"AlreadySeenTxs":162036,"AlreadyRejectedTxs":0,"RequestedTxs":0,"RerequestedTxs":0,"LostTxs":0,"FailedResponses":0,"SentTransactionBytes":896374034,"SentStateBytes":0,"ReceivedTxBytes":905194960,"ReceivedStateBytes":0},{"StartedAt":"2022-12-20T17:23:11.404644174Z","EndedAt":"2022-12-20T17:35:21.412121783Z","FailedTxs":0,"EvictedTxs":0,"SuccessfulTxs":11040,"AlreadySeenTxs":206926,"AlreadyRejectedTxs":0,"RequestedTxs":0,"RerequestedTxs":0,"LostTxs":0,"FailedResponses":0,"SentTransactionBytes":1176856826,"SentStateBytes":0,"ReceivedTxBytes":1176557056,"ReceivedStateBytes":0},{"StartedAt":"2022-12-20T17:23:11.404644174Z","EndedAt":"2022-12-20T17:35:51.411907323Z","FailedTxs":0,"EvictedTxs":0,"SuccessfulTxs":11924,"AlreadySeenTxs":221611,"AlreadyRejectedTxs":0,"RequestedTxs":0,"RerequestedTxs":0,"LostTxs":0,"FailedResponses":0,"SentTransactionBytes":1275039778,"SentStateBytes":0,"ReceivedTxBytes":1265505232,"ReceivedStateBytes":0}]