[{"StartedAt":"2023-01-09T15:27:47.835449057Z","EndedAt":"2023-01-09T15:30:57.843946592Z","Blocks":12,"FailedTxs":0,"EvictedTxs":0,"SuccessfulTxs":200,"SuccessfulBytes":747200,"AlreadySeenTxs":44,"AlreadyRejectedTxs":0,"RequestedTxs":287,"RerequestedTxs":41,"LostTxs":0,"FailedResponses":0,"SentTransactionBytes":808272,"SentStateBytes":193400,"ReceivedTxBytes":1276022,"ReceivedStateBytes":258618},{"StartedAt":"2023-01-09T15:27:47.835449057Z","EndedAt":"2023-01-09T15:31:27.84391147Z","Blocks":14,"FailedTxs":0,"EvictedTxs":0,"SuccessfulTxs":400,"SuccessfulBytes":1494400,"AlreadySeenTxs":62,"AlreadyRejectedTxs":0,"RequestedTxs":466,"RerequestedTxs":58,"LostTxs":0,"FailedResponses":0,"SentTransactionBytes":1189956,"SentStateBytes":319098,"ReceivedTxBytes":2065584,"ReceivedStateBytes":410582},{"StartedAt":"2023-01-09T15:27:47.835449057Z","EndedAt":"2023-01-09T15:32:07.843277968Z","Blocks":16,"FailedTxs":0,"EvictedTxs":0,"SuccessfulTxs":600,"SuccessfulBytes":2241600,"AlreadySeenTxs":106,"AlreadyRejectedTxs":0,"RequestedTxs":673,"RerequestedTxs":100,"LostTxs":0,"FailedResponses":0,"SentTransactionBytes":2028164,"SentStateBytes":448226,"ReceivedTxBytes":2989858,"ReceivedStateBytes":591426},{"StartedAt":"2023-01-09T15:27:47.835449057Z","EndedAt":"2023-01-09T15:32:37.843559678Z","Blocks":18,"FailedTxs":0,"EvictedTxs":0,"SuccessfulTxs":800,"SuccessfulBytes":2988800,"AlreadySeenTxs":137,"AlreadyRejectedTxs":0,"RequestedTxs":866,"RerequestedTxs":129,"LostTxs":0,"FailedResponses":0,"SentTransactionBytes":3001084,"SentStateBytes":578942,"ReceivedTxBytes":3846776,"ReceivedStateBytes":748556},{"StartedAt":"2023-01-09T15:27:47.835449057Z","EndedAt":"2023-01-09T15:33:17.843555996Z","Blocks":21,"FailedTxs":0,"EvictedTxs":0,"SuccessfulTxs":1100,"SuccessfulBytes":4109600,"AlreadySeenTxs":245,"AlreadyRejectedTxs":0,"RequestedTxs":1218,"RerequestedTxs":236,"LostTxs":0,"FailedResponses":0,"SentTransactionBytes":3843034,"SentStateBytes":782706,"ReceivedTxBytes":5362286,"ReceivedStateBytes":1008598},{"StartedAt":"2023-01-09T15:27:47.835449057Z","EndedAt":"2023-01-09T15:33:57.843590512Z","Blocks":23,"FailedTxs":0,"EvictedTxs":0,"SuccessfulTxs":1300,"SuccessfulBytes":4856800,"AlreadySeenTxs":315,"AlreadyRejectedTxs":0,"RequestedTxs":1449,"RerequestedTxs":303,"LostTxs":0,"FailedResponses":0,"SentTransactionBytes":4423044,"SentStateBytes":910478,"ReceivedTxBytes":6365142,"ReceivedStateBytes":1186198},{"StartedAt":"2023-01-09T15:27:47.835449057Z","EndedAt":"2023-01-09T15:34:27.843498357Z","Blocks":25,"FailedTxs":0,"EvictedTxs":0,"SuccessfulTxs":1500,"SuccessfulBytes":5604000,"AlreadySeenTxs":353,"AlreadyRejectedTxs":0,"RequestedTxs":1649,"RerequestedTxs":340,"LostTxs":0,"FailedResponses":0,"SentTransactionBytes":5384738,"SentStateBytes":1039726,"ReceivedTxBytes":7248254,"ReceivedStateBytes":1355102},{"StartedAt":"2023-01-09T15:27:47.835449057Z","EndedAt":"2023-01-09T15:35:07.843646999Z","Blocks":28,"FailedTxs":0,"EvictedTxs":0,"SuccessfulTxs":1800,"SuccessfulBytes":6724800,"AlreadySeenTxs":443,"AlreadyRejectedTxs":0,"RequestedTxs":1983,"RerequestedTxs":426,"LostTxs":0,"FailedResponses":0,"SentTransactionBytes":6279076,"SentStateBytes":1232300,"ReceivedTxBytes":8696408,"ReceivedStateBytes":1622322},{"StartedAt":"2023-01-09T15:27:47.835449057Z","EndedAt":"2023-01-09T15:35:47.843512534Z","Blocks":30,"FailedTxs":0,"EvictedTxs":0,"SuccessfulTxs":2000,"SuccessfulBytes":7472000,"AlreadySeenTxs":506,"AlreadyRejectedTxs":0,"RequestedTxs":2207,"RerequestedTxs":488,"LostTxs":0,"FailedResponses":0,"SentTransactionBytes":7480258,"SentStateBytes":1360528,"ReceivedTxBytes":9673070,"ReceivedStateBytes":1802182},{"StartedAt":"2023-01-09T15:27:47.835449057Z","EndedAt":"2023-01-09T15:36:17.843321129Z","Blocks":32,"FailedTxs":0,"EvictedTxs":0,"SuccessfulTxs":2200,"SuccessfulBytes":8219200,"AlreadySeenTxs":516,"AlreadyRejectedTxs":0,"RequestedTxs":2298,"RerequestedTxs":498,"LostTxs":0,"FailedResponses":0,"SentTransactionBytes":7817038,"SentStateBytes":1420200,"ReceivedTxBytes":10080948,"ReceivedStateBytes":1896800},{"StartedAt":"2023-01-09T15:27:47.835449057Z","EndedAt":"2023-01-09T15:36:57.843278291Z","Blocks":35,"FailedTxs":0,"EvictedTxs":0,"SuccessfulTxs":2200,"SuccessfulBytes":8219200,"AlreadySeenTxs":1324,"AlreadyRejectedTxs":0,"RequestedTxs":3998,"RerequestedTxs":1273,"LostTxs":22,"FailedResponses":0,"SentTransactionBytes":15571758,"SentStateBytes":2190252,"ReceivedTxBytes":20897642,"ReceivedStateBytes":2975398},{"StartedAt":"2023-01-09T15:27:47.835449057Z","EndedAt":"2023-01-09T15:37:27.843577587Z","Blocks":36,"FailedTxs":0,"EvictedTxs":0,"SuccessfulTxs":3084,"SuccessfulBytes":8515340,"AlreadySeenTxs":1535,"AlreadyRejectedTxs":0,"RequestedTxs":4914,"RerequestedTxs":1468,"LostTxs":23,"FailedResponses":0,"SentTransactionBytes":24064996,"SentStateBytes":2814584,"ReceivedTxBytes":27103476,"ReceivedStateBytes":3702950},{"StartedAt":"2023-01-09T15:27:47.835449057Z","EndedAt":"2023-01-09T15:38:07.843367645Z","Blocks":39,"FailedTxs":0,"EvictedTxs":0,"SuccessfulTxs":5736,"SuccessfulBytes":9408632,"AlreadySeenTxs":2130,"AlreadyRejectedTxs":0,"RequestedTxs":7650,"RerequestedTxs":2088,"LostTxs":28,"FailedResponses":0,"SentTransactionBytes":45432180,"SentStateBytes":4525242,"ReceivedTxBytes":44569124,"ReceivedStateBytes":5629686},{"StartedAt":"2023-01-09T15:27:47.835449057Z","EndedAt":"2023-01-09T15:38:37.844277312Z","Blocks":40,"FailedTxs":0,"EvictedTxs":0,"SuccessfulTxs":6620,"SuccessfulBytes":9706540,"AlreadySeenTxs":2330,"AlreadyRejectedTxs":0,"RequestedTxs":8557,"RerequestedTxs":2241,"LostTxs":28,"FailedResponses":0,"SentTransactionBytes":62002300,"SentStateBytes":5235124,"ReceivedTxBytes":51533708,"ReceivedStateBytes":6506148},{"StartedAt":"2023-01-09T15:27:47.835449057Z","EndedAt":"2023-01-09T15:39:17.843770727Z","Blocks":42,"FailedTxs":0,"EvictedTxs":0,"SuccessfulTxs":8392,"SuccessfulBytes":10303704,"AlreadySeenTxs":2680,"AlreadyRejectedTxs":0,"RequestedTxs":10361,"RerequestedTxs":2580,"LostTxs":28,"FailedResponses":0,"SentTransactionBytes":73507268,"SentStateBytes":6388730,"ReceivedTxBytes":63580556,"ReceivedStateBytes":7961636},{"StartedAt":"2023-01-09T15:27:47.835449057Z","EndedAt":"2023-01-09T15:39:47.843771389Z","Blocks":44,"FailedTxs":0,"EvictedTxs":0,"SuccessfulTxs":10160,"SuccessfulBytes":10899520,"AlreadySeenTxs":3275,"AlreadyRejectedTxs":0,"RequestedTxs":12391,"RerequestedTxs":3141,"LostTxs":34,"FailedResponses":0,"SentTransactionBytes":90111612,"SentStateBytes":7648144,"ReceivedTxBytes":76984956,"ReceivedStateBytes":9297744},{"StartedAt":"2023-01-09T15:27:47.835449057Z","EndedAt":"2023-01-09T15:40:27.84402873Z","Blocks":46,"FailedTxs":0,"EvictedTxs":0,"SuccessfulTxs":11960,"SuccessfulBytes":11506120,"AlreadySeenTxs":3527,"AlreadyRejectedTxs":0,"RequestedTxs":13749,"RerequestedTxs":3372,"LostTxs":34,"FailedResponses":0,"SentTransactionBytes":98114324,"SentStateBytes":8515432,"ReceivedTxBytes":86082836,"ReceivedStateBytes":10470696},{"StartedAt":"2023-01-09T15:27:47.835449057Z","EndedAt":"2023-01-09T15:40:37.843778906Z","Blocks":47,"FailedTxs":0,"EvictedTxs":0,"SuccessfulTxs":12621,"SuccessfulBytes":11728877,"AlreadySeenTxs":3552,"AlreadyRejectedTxs":0,"RequestedTxs":14034,"RerequestedTxs":3395,"LostTxs":34,"FailedResponses":0,"SentTransactionBytes":99300756,"SentStateBytes":8712300,"ReceivedTxBytes":87987972,"ReceivedStateBytes":10717372}]